MANIFEST.in
setup.py
grpc_help/__init__.py
grpc_help/client.py
grpc_help/exceptions.py
grpc_help/generic_client_interceptor.py
grpc_help/grpcserver.py
grpc_help/interceptor.py
grpc_help/key.py
grpc_help/rules.py
grpc_help/utils.py
grpc_help/views.py
grpc_help.egg-info/PKG-INFO
grpc_help.egg-info/SOURCES.txt
grpc_help.egg-info/dependency_links.txt
grpc_help.egg-info/not-zip-safe
grpc_help.egg-info/requires.txt
grpc_help.egg-info/top_level.txt
grpc_help/__pycache__/__init__.cpython-36.pyc
grpc_help/__pycache__/client.cpython-36.pyc
grpc_help/__pycache__/exceptions.cpython-36.pyc
grpc_help/__pycache__/generic_client_interceptor.cpython-36.pyc
grpc_help/__pycache__/grpcserver.cpython-36.pyc
grpc_help/__pycache__/interceptor.cpython-36.pyc
grpc_help/__pycache__/key.cpython-36.pyc
grpc_help/__pycache__/rules.cpython-36.pyc
grpc_help/__pycache__/utils.cpython-36.pyc
grpc_help/__pycache__/views.cpython-36.pyc
grpc_help/management/__init__.py
grpc_help/management/commands/__init__.py
grpc_help/management/commands/run_grpc_server.py